inststd/__init__.py
stdclasses/__init__.py
stdclasses/conceitos.py
stdclasses/enviaremail.py
stdclasses/funcoes.py
stdclasses/spark.py
inststd-0.2.5.dist-info/METADATA
inststd-0.2.5.dist-info/WHEEL
inststd-0.2.5.dist-info/top_level.txt
inststd-0.2.5.dist-info/RECORD
