Metadata-Version: 2.1
Name: inststd
Version: 0.2.5
Summary: instalador
Home-page: https://github.com/guimartino/stdclasses
Author: Guilherme Martino
Author-email: gui.martino@hotmail.com
License: MIT
Platform: UNKNOWN
Classifier: Development Status :: 4 - Beta
Classifier: Intended Audience :: System Administrators
Classifier: License :: OSI Approved :: Apache Software License
Classifier: Programming Language :: Python :: 3
Requires-Dist: requests
Requires-Dist: pip
